sema4ai/mcp/__init__.py
sema4ai/mcp/_validate_prompt.py
sema4ai/mcp/_validate_resource.py
sema4ai/mcp/py.typed
sema4ai_mcp-0.0.1.dist-info/METADATA
sema4ai_mcp-0.0.1.dist-info/WHEEL
sema4ai_mcp-0.0.1.dist-info/RECORD
