Metadata-Version: 2.3
Name: sema4ai-mcp
Version: 0.0.1
Summary: Sema4AI Model Context Protocol (MCP)
License: Apache-2.0
Author: Sema4.ai Engineering
Author-email: engineering@sema4.ai
Requires-Python: >=3.10,<4.0
Classifier: License :: OSI Approved :: Apache Software License
Classifier: Programming Language :: Python :: 3
Classifier: Programming Language :: Python :: 3.10
Classifier: Programming Language :: Python :: 3.11
Classifier: Programming Language :: Python :: 3.12
Classifier: Programming Language :: Python :: 3.13
Requires-Dist: sema4ai-actions (>=1.3.13,<2.0.0)
Project-URL: Repository, https://github.com/Sema4AI/actions/
